LICENSE
pyproject.toml
.github/README.md
scenario_labs/__init__.py
scenario_labs/experiment.py
scenario_labs/agents/LLMAgent.py
scenario_labs/agents/__init__.py
scenario_labs/logging/conversation_logger.py
scenario_labs/logging/oneshot_logger.py
scenario_labs/providers/base.py
scenario_labs/providers/factory.py
scenario_labs/providers/google.py
scenario_labs/providers/openai.py
scenario_labs/providers/xai.py
scenario_labs/simulations/conversation.py
scenario_labs/simulations/oneshot.py
scenario_labs-0.0.11.dist-info/METADATA
scenario_labs-0.0.11.dist-info/WHEEL
scenario_labs-0.0.11.dist-info/entry_points.txt
scenario_labs-0.0.11.dist-info/licenses/LICENSE
scenario_labs-0.0.11.dist-info/RECORD
